tiktoken_async/load.py
tiktoken_async/__init__.py
tiktoken_async/_tiktoken.cpython-310-x86_64-linux-gnu.so
tiktoken_async/core.py
tiktoken_async/registry.py
tiktoken_async/model.py
tiktoken_async/py.typed
tiktoken_async_ext/openai_public.py
tiktoken_async-0.3.2.dist-info/LICENSE
tiktoken_async-0.3.2.dist-info/WHEEL
tiktoken_async-0.3.2.dist-info/top_level.txt
tiktoken_async-0.3.2.dist-info/RECORD
tiktoken_async-0.3.2.dist-info/METADATA
