Metadata-Version: 2.1
Name: tiktoken-async
Version: 0.3.2
Summary: tiktoken-async is a fast BPE tokeniser for use with OpenAI's models, with added support for asynchronous processing.
Author: Shantanu Jain
Author-email: shantanu@openai.com
License: MIT License
Project-URL: homepage, https://github.com/djkcyl/tiktoken-async
Project-URL: repository, https://github.com/djkcyl/tiktoken-async
Project-URL: changelog, https://github.com/openai/tiktoken/blob/main/CHANGELOG.md
Requires-Python: >=3.8
Provides-Extra: blobfile
License-File: LICENSE
